carla_gym/__init__.py
carla_gym/multi_env.py
carla_gym/carla_api/__init__.py
carla_gym/carla_api/reward.py
carla_gym/carla_api/utils.py
carla_gym/carla_api/PythonAPI/.gitignore
carla_gym/carla_api/PythonAPI/README.md
carla_gym/carla_api/PythonAPI/__init__.py
carla_gym/carla_api/PythonAPI/converter.py
carla_gym/carla_api/PythonAPI/dynamic_weather.py
carla_gym/carla_api/PythonAPI/manual_control.py
carla_gym/carla_api/PythonAPI/scenarios.py
carla_gym/carla_api/PythonAPI/settings.py
carla_gym/carla_api/PythonAPI/setup.py
carla_gym/carla_api/PythonAPI/tutorial.py
carla_gym/carla_api/PythonAPI/vehicle_gallery.py
carla_gym/carla_api/PythonAPI/agents/__init__.py
carla_gym/carla_api/PythonAPI/agents/navigation/__init__.py
carla_gym/carla_api/PythonAPI/agents/navigation/agent.py
carla_gym/carla_api/PythonAPI/agents/navigation/basic_agent.py
carla_gym/carla_api/PythonAPI/agents/navigation/controller.py
carla_gym/carla_api/PythonAPI/agents/navigation/global_route_planner.py
carla_gym/carla_api/PythonAPI/agents/navigation/global_route_planner_dao.py
carla_gym/carla_api/PythonAPI/agents/navigation/local_planner.py
carla_gym/carla_api/PythonAPI/agents/navigation/roaming_agent.py
carla_gym/carla_api/PythonAPI/agents/navigation/test_global_route_planner.py
carla_gym/carla_api/PythonAPI/agents/tools/__init__.py
carla_gym/carla_api/PythonAPI/agents/tools/misc.py
carla_gym/carla_api/PythonAPI/source/carla/__init__.py
carla_gym/carla_api/PythonAPI/source/libcarla/Actor.cpp
carla_gym/carla_api/PythonAPI/source/libcarla/Blueprint.cpp
carla_gym/carla_api/PythonAPI/source/libcarla/Client.cpp
carla_gym/carla_api/PythonAPI/source/libcarla/Control.cpp
carla_gym/carla_api/PythonAPI/source/libcarla/Exception.cpp
carla_gym/carla_api/PythonAPI/source/libcarla/Geom.cpp
carla_gym/carla_api/PythonAPI/source/libcarla/Sensor.cpp
carla_gym/carla_api/PythonAPI/source/libcarla/SensorData.cpp
carla_gym/carla_api/PythonAPI/source/libcarla/Weather.cpp
carla_gym/carla_api/PythonAPI/source/libcarla/World.cpp
carla_gym-1.0.0.dist-info/LICENSE
carla_gym-1.0.0.dist-info/METADATA
carla_gym-1.0.0.dist-info/WHEEL
carla_gym-1.0.0.dist-info/top_level.txt
carla_gym-1.0.0.dist-info/RECORD
