Metadata-Version: 2.1
Name: carla-gym
Version: 1.0.0
Summary: Multi-agent reinforcement learning interface for CARLA Autonomous Driving simulator compatible with PettingZoo.
Home-page: https://github.com/johnMinelli/carla-gym
License: MIT
License-File: LICENSE
Requires-Dist: gymnasium
Requires-Dist: pettingzoo
Requires-Dist: carla (>=0.9.3)
Requires-Dist: GPUtil
Requires-Dist: pygame
Requires-Dist: opencv-python
Requires-Dist: networkx (==2.6.3)
Requires-Dist: psutil
Provides-Extra: test
Requires-Dist: tox ; extra == 'test'
Requires-Dist: pytest ; extra == 'test'
Requires-Dist: pytest-xdist ; extra == 'test'
